lm_polygraph/__init__.py
lm_polygraph/defaults/register_default_stat_calculators.py
lm_polygraph/defaults/stat_calculator_builders/default_ClaimsExtractor.py
lm_polygraph/defaults/stat_calculator_builders/default_ConcatGreedySemanticMatrixCalculator.py
lm_polygraph/defaults/stat_calculator_builders/default_CrossEncoderSimilarityMatrixCalculator.py
lm_polygraph/defaults/stat_calculator_builders/default_CrossEncoderSimilarityMatrixVisualCalculator.py
lm_polygraph/defaults/stat_calculator_builders/default_GreedyAlternativesFactPrefNLICalculator.py
lm_polygraph/defaults/stat_calculator_builders/default_GreedyAlternativesNLICalculator.py
lm_polygraph/defaults/stat_calculator_builders/default_GreedyCrossEncoderSimilarityMatrixCalculator.py
lm_polygraph/defaults/stat_calculator_builders/default_GreedyProbsCalculator.py
lm_polygraph/defaults/stat_calculator_builders/default_GreedyProbsVisualCalculator.py
lm_polygraph/defaults/stat_calculator_builders/default_GreedySemanticMatrixCalculator.py
lm_polygraph/defaults/stat_calculator_builders/default_SemanticClassesClaimToSamplesCalculator.py
lm_polygraph/defaults/stat_calculator_builders/default_SemanticMatrixCalculator.py
lm_polygraph/defaults/stat_calculator_builders/default_TrainingStatisticExtractionCalculator.py
lm_polygraph/defaults/stat_calculator_builders/default_TrainingStatisticExtractionCalculatorVisual.py
lm_polygraph/defaults/stat_calculator_builders/utils.py
lm_polygraph/estimators/__init__.py
lm_polygraph/estimators/attention_score.py
lm_polygraph/estimators/claim_conditioned_probability.py
lm_polygraph/estimators/cocoa.py
lm_polygraph/estimators/common.py
lm_polygraph/estimators/conditional_pointwise_mutual_information.py
lm_polygraph/estimators/csl.py
lm_polygraph/estimators/deg_mat.py
lm_polygraph/estimators/eccentricity.py
lm_polygraph/estimators/eig_val_laplacian.py
lm_polygraph/estimators/eigenscore.py
lm_polygraph/estimators/ensemble_sequence_measures.py
lm_polygraph/estimators/ensemble_token_measures.py
lm_polygraph-0.5.0.dist-info/licenses/LICENSE.md
lm_polygraph-0.5.0.dist-info/METADATA
lm_polygraph-0.5.0.dist-info/WHEEL
lm_polygraph-0.5.0.dist-info/top_level.txt
lm_polygraph-0.5.0.dist-info/RECORD
