Metadata-Version: 2.4
Name: lm_polygraph
Version: 0.5.0
Summary: Uncertainty Estimation Toolkit for Transformer Language Models
Author-email: "List of contributors: https://github.com/IINemo/lm-polygraph/graphs/contributors" <artemshelmanov@gmail.com>
License: Copyright (c) 2023 MBZUAI
Project-URL: Homepage, https://github.com/IINemo/lm-polygraph
Project-URL: Bug Tracker, https://github.com/IINemo/lm-polygraph/issues
Project-URL: Repository, https://github.com/IINemo/lm-polygraph
Project-URL: Documentation, https://lm-polygraph.readthedocs.io
Keywords: NLP,deep learning,transformer,pytorch,uncertainty estimation
Classifier: Development Status :: 3 - Alpha
Classifier: Intended Audience :: Developers
Classifier: Intended Audience :: Education
Classifier: Intended Audience :: Science/Research
Classifier: License :: OSI Approved :: MIT License
Classifier: Operating System :: OS Independent
Classifier: Programming Language :: Python :: 3
Classifier: Programming Language :: Python :: 3.10
Classifier: Programming Language :: Python :: 3.11
Classifier: Topic :: Scientific/Engineering :: Artificial Intelligence
Requires-Python: >=3.10
License-File: LICENSE.md
Requires-Dist: datasets<4.0.0,>=2.19.0
Requires-Dist: rouge-score>=0.0.4
Requires-Dist: nlpaug>=1.1.10
Requires-Dist: scikit-learn>=1.5.1
Requires-Dist: tqdm>=4.64.1
Requires-Dist: matplotlib>=3.6
Requires-Dist: pandas>=1.3.5
Requires-Dist: torch>=2.6.0
Requires-Dist: bs4
Requires-Dist: transformers==4.50.0
Requires-Dist: nltk>=3.6.5
Requires-Dist: sacrebleu>=1.5.0
Requires-Dist: sentencepiece>=0.1.97
Requires-Dist: hf-lfs>=0.0.3
Requires-Dist: pytest>=4.4.1
Requires-Dist: pytreebank>=0.2.7
Requires-Dist: setuptools>=60.2.0
Requires-Dist: numpy>=1.23.5
Requires-Dist: dill>=0.3.5.1
Requires-Dist: scipy>=1.9.3
Requires-Dist: flask>=2.3.2
Requires-Dist: protobuf>=4.23
Requires-Dist: fschat>=0.2.3
Requires-Dist: hydra-core>=1.3.2
Requires-Dist: einops
Requires-Dist: accelerate>=0.32.1
Requires-Dist: bitsandbytes
Requires-Dist: openai>=1.52.0
Requires-Dist: wget
Requires-Dist: sentence-transformers
Requires-Dist: bert-score>=0.3.13
Requires-Dist: unbabel-comet==2.2.1
Requires-Dist: nltk<4,>=3.7
Requires-Dist: evaluate>=0.4.2
Requires-Dist: spacy<3.8.0,>=3.4.0
Requires-Dist: fastchat
Requires-Dist: diskcache>=5.6.3
Dynamic: license-file
